surquest/GCP/bq/grid/__init__.py
surquest/GCP/bq/grid/field.py
surquest/GCP/bq/grid/grid.py
surquest_gcp_bq_grid-0.0.1rc7.dist-info/METADATA
surquest_gcp_bq_grid-0.0.1rc7.dist-info/WHEEL
surquest_gcp_bq_grid-0.0.1rc7.dist-info/licenses/LICENSE
surquest_gcp_bq_grid-0.0.1rc7.dist-info/RECORD
