Metadata-Version: 2.1
Name: surquest-GCP-bq-grid
Version: 0.0.1rc7
Summary: Wrapper around Google Cloud Platform BigQuery client to simplify management of the BigQuery tables.
Project-URL: Homepage, https://github.com/surquest/python-gcp-tracer
Project-URL: Bug Tracker, https://github.com/surquest/python-gcp-tracer/issues
Author-email: Michal Švarc <michal.svarc@surquest.com>
License-File: LICENSE
Requires-Dist: google-cloud-bigquery>=3.5.0
Requires-Dist: google-cloud-storage>=2.7.0
Requires-Dist: pyyaml>=6.0
Provides-Extra: test
Requires-Dist: pytest-cov>=4.0.0; extra == 'test'
Requires-Dist: pytest>=7.2.1; extra == 'test'
